listgits/__init__.py
listgits/listgits.py
listgits-2.0.0.dist-info/LICENSE
listgits-2.0.0.dist-info/METADATA
listgits-2.0.0.dist-info/WHEEL
listgits-2.0.0.dist-info/entry_points.txt
listgits-2.0.0.dist-info/top_level.txt
listgits-2.0.0.dist-info/RECORD
