Metadata-Version: 2.1
Name: listgits
Version: 2.0.0
Summary: Python command line program for listing git repositories under a folder root, and optionally run any git command on those repos
Home-page: https://github.com/OsirisTerje/listgits
Author: Terje Sandstrom
Author-email: terje@hermit.no
License: UNKNOWN
Platform: UNKNOWN
Classifier: Programming Language :: Python :: 3
Classifier: License :: OSI Approved :: MIT License
Classifier: Operating System :: OS Independent
Requires-Python: >=3.10
License-File: LICENSE
